dadosgovbr-0.1.3.dist-info/WHEEL
dadosgovbr-0.1.3.dist-info/metadata.json
dadosgovbr-0.1.3.dist-info/DESCRIPTION.rst
dadosgovbr-0.1.3.dist-info/top_level.txt
dadosgovbr-0.1.3.dist-info/METADATA
dadosgovbr-0.1.3.dist-info/RECORD
dadosgovbr/__init__.py
dadosgovbr/exceptions.py
dadosgovbr/client.py
dadosgovbr/factory.py
