Metadata-Version: 2.0
Name: dadosgovbr
Version: 0.1.3
Summary: A library to programatically explore the Brazillian open data program
Home-page: https://github.com/georgeyk/dadosgovbr
Author: George Y. Kussumoto
Author-email: contato@georgeyk.com.br
License: MIT
Platform: UNKNOWN
Classifier: Development Status :: 3 - Alpha
Classifier: Environment :: Console
Classifier: Intended Audience :: Developers
Classifier: Intended Audience :: Information Technology
Classifier: License :: OSI Approved :: MIT License
Classifier: Operating System :: OS Independent
Classifier: Programming Language :: Python :: 2.7
Classifier: Programming Language :: Python :: 3
Classifier: Programming Language :: Python :: 3.4
Classifier: Topic :: Internet :: WWW/HTTP :: Dynamic Content
Requires-Dist: requests
